Workbook
Name lista_status_documento: 'Apoio'!$A$4:$A$7
Name lista_categorias_rendimento: 'Apoio'!$B$4:$B$11
Name lista_grupos_bens: 'Apoio'!$C$4:$C$11
Name lista_categorias_pagamento: 'Apoio'!$D$4:$D$11
Name lista_prioridades: 'Apoio'!$E$4:$E$7
Name lista_status_nota: 'Apoio'!$F$4:$F$6
Name lista_estados_civis: 'Apoio'!$G$4:$G$9
Name lista_ufs: 'Apoio'!$H$4:$H$30
Name lista_relacoes_dependente: 'Apoio'!$I$4:$I$11
Name lista_sim_nao: 'Apoio'!$J$4:$J$5
Name lista_titular_dependente: 'Apoio'!$K$4:$K$5
Name lista_categorias_informe: 'Apoio'!$L$4:$L$12
Name lista_tipos_declaracao: 'Apoio'!$M$4:$M$5
Name lista_status_cadastro: 'Apoio'!$N$4:$N$6
Name lista_categorias_nota: 'Apoio'!$O$4:$O$11
Name lista_paises: 'Apoio'!$P$4:$P$7
Name ano_calendario: 'Início'!$C$6
Name exercicio_declaracao: 'Início'!$G$6
Name nome_titular: 'Titular'!$C$8
Name cpf_titular: 'Titular'!$C$9
Name dados_rendimentos: 'Rendimentos'!$A$9:$J$38
Name dados_bens: 'Bens'!$A$9:$K$38
Name dados_pagamentos: 'Pagamentos'!$A$9:$K$38
Name dados_informes: 'Informes'!$A$9:$I$38

Sheet Início
A1: IR PANORAMA | I1: PROJETO AUTORAL • DADOS FICTÍCIOS
A2: INÍCIO | B2: TITULAR | C2: DEPENDENTES | D2: RENDIMENTOS | E2: BENS | F2: PAGAMENTOS | G2: INFORMES | H2: NOTAS | I2: GUIA | N2: Status | O2: Quantidade
A3: Organizador autoral para reunir documentos, dados e pendências da declaração de Imposto de Renda. | N3: Conferido | O3: =COUNTIF(Informes!$H$9:$H$38,"Conferido") -> 5
N4: Recebido | O4: =COUNTIF(Informes!$H$9:$H$38,"Recebido") -> 2
A5: VISÃO GERAL DA ORGANIZAÇÃO | N5: Pendente | O5: =COUNTIF(Informes!$H$9:$H$38,"Pendente") -> 1
A6: ANO-CALENDÁRIO | C6: 2025 | E6: EXERCÍCIO | G6: =ano_calendario+1 -> 2026 | I6: MODO | K6: DEMONSTRAÇÃO | N6: Não se aplica | O6: =COUNTIF(Informes!$H$9:$H$38,"Não se aplica") -> 0
A9: RENDIMENTOS BRUTOS | D9: BENS — SITUAÇÃO ATUAL | G9: PAGAMENTOS LÍQUIDOS | J9: DOCUMENTOS CONFERIDOS
A10: =SUM(Rendimentos!$E$9:$E$38) -> 93830.75 | D10: =SUM(Bens!$H$9:$H$38) -> 337650.75 | G10: =SUM(Pagamentos!$H$9:$H$38) -> 12460 | J10: =IFERROR((COUNTIF(Informes!$H$9:$H$38,"Conferido")+COUNTIF(Informes!$H$9:$H$38,"Não se aplica"))/COUNTIF(Informes!$A$9:$A$38,"<>"),0) -> 0.625
A14: IR RETIDO INFORMADO | D14: INSS INFORMADO | G14: PENDÊNCIAS ABERTAS | J14: REGISTROS FINANCEIROS
A15: =SUM(Rendimentos!$F$9:$F$38) -> 7800 | D15: =SUM(Rendimentos!$G$9:$G$38) -> 7260 | G15: =COUNTIFS(Informes!$A$9:$A$38,"<>",Informes!$H$9:$H$38,"<>Conferido",Informes!$H$9:$H$38,"<>Não se aplica")+COUNTIFS(Notas!$A$9:$A$38,"<>",Notas!$G$9:$G$38,"<>Concluída") -> 5 | J15: =COUNTA(Rendimentos!$A$9:$A$38)+COUNTA(Bens!$A$9:$A$38)+COUNTA(Pagamentos!$A$9:$A$38) -> 11
A18: PROGRESSO DA CONFERÊNCIA DOCUMENTAL
A19: =IFERROR((COUNTIF(Informes!$H$9:$H$38,"Conferido")+COUNTIF(Informes!$H$9:$H$38,"Não se aplica"))/COUNTIF(Informes!$A$9:$A$38,"<>"),0) -> 0.625
A22: MENU PRINCIPAL — CLIQUE EM UMA ÁREA
A23: 01 TITULAR Cadastro e parâmetros da declaração | D23: 02 DEPENDENTES Relações e conferência cadastral | G23: 03 RENDIMENTOS Fontes, IRRF e INSS | J23: 04 BENS Saldos anterior e atual
A28: 05 PAGAMENTOS Valores, reembolsos e documentos | D28: 06 INFORMES Checklist de documentos | G28: 07 NOTAS Prazos, prioridades e alertas | J28: 08 GUIA Uso, privacidade e validação
A33: RESUMO DE REVISÃO
A35: Cadastro do titular | C35: =IF(COUNTA(Titular!$C$8:$C$20)>=10,"Pronto","Revisar") -> Pronto
A37: Informes | C37: =COUNTIF(Informes!$H$9:$H$38,"Conferido")&" de "&COUNTIF(Informes!$A$9:$A$38,"<>")&" conferidos" -> 5 de 8 conferidos
A39: Notas | C39: =COUNTIFS(Notas!$A$9:$A$38,"<>",Notas!$G$9:$G$38,"<>Concluída")&" notas abertas" -> 2 notas abertas
A41: Documentos | C41: =IF(COUNTIF(Informes!$H$9:$H$38,"Pendente")=0,"Sem documentos pendentes",COUNTIF(Informes!$H$9:$H$38,"Pendente")&" documento(s) pendente(s)") -> 1 documento(s) pendente(s)
A43: Próxima ação | C43: =IF(G15=0,"Pronto para revisão final","Revise as pendências") -> Revise as pendências
A46: LINKS OFICIAIS — ABREM NO NAVEGADOR
A47: MEU IMPOSTO DE RENDA | E47: PORTAL e-CAC | I47: PORTAL GOV.BR
A50: Autoria: 0Barone (@gabrielnasciimentoleandro-arch) • Arquivo demonstrativo com dados fictícios • Não substitui o programa oficial nem orientação profissional.

Sheet Titular
A1: TITULAR | I1: PROJETO AUTORAL • DADOS FICTÍCIOS
A2: INÍCIO | B2: TITULAR | C2: DEPENDENTES | D2: RENDIMENTOS | E2: BENS | F2: PAGAMENTOS | G2: INFORMES | H2: NOTAS | I2: GUIA
A3: Cadastre os dados básicos na cópia privada. Os valores deste arquivo são fictícios.
B5: DADOS DO TITULAR | F5: CONFERÊNCIA AUTOMÁTICA
B8: Nome completo | C8: Marina Exemplo | F8: Situação do cadastro | H8: =IF(COUNTA(C8:C20)>=10,"Cadastro consistente","Complete os campos") -> Cadastro consistente
B9: CPF | C9: 000.000.000-00
B10: Data de nascimento | C10: 32888
B11: E-mail | C11: marina.exemplo@exemplo.invalid | F11: Preenchimento | H11: =COUNTA(C8:C20)/13 -> 1
B12: Telefone | C12: (00) 00000-0000
B13: Ocupação | C13: Analista de projetos
B14: Estado civil | C14: Solteiro(a) | F14: Declaração | H14: =C19&" • Exercício "&Início!G6 -> Original • Exercício 2026
B15: Endereço | C15: Endereço fictício para demonstração
B16: Cidade | C16: Cidade Exemplo
B17: UF | C17: SP | F17: Residência | H17: =IF(C20="Sim","Residente no Brasil","Revisar residência") -> Residente no Brasil
B18: CEP | C18: 00000-000
B19: Tipo de declaração | C19: Original
B20: Residente no Brasil? | C20: Sim
F21: PRIVACIDADE: nunca publique uma versão preenchida com seus dados reais. Faça uma cópia privada, mantenha backup protegido e deixe no GitHub somente o modelo demonstrativo.
B23: VOLTAR AO PAINEL
B27: Os dados desta aba servem para organização e revisão. A transmissão da declaração deve ser feita somente pelos canais oficiais da Receita Federal.

Sheet Dependentes
A1: DEPENDENTES | I1: PROJETO AUTORAL • DADOS FICTÍCIOS
A2: INÍCIO | B2: TITULAR | C2: DEPENDENTES | D2: RENDIMENTOS | E2: BENS | F2: PAGAMENTOS | G2: INFORMES | H2: NOTAS | I2: GUIA
A3: Organize os dados cadastrais e marque os itens que ainda precisam de revisão.
A5: REGISTROS — 1 EXEMPLO(S) FICTÍCIO(S) PREENCHIDO(S)
A6: Adicione novas linhas dentro da tabela. Células azul-claro são editáveis; colunas cinza contêm fórmulas.
A8: ID | B8: Nome | C8: CPF | D8: Nascimento | E8: Relação | F8: Reside com titular? | G8: Status | H8: Observações
A9: DEP-001 | B9: Lucas Exemplo | C9: 000.000.000-00 | D9: 41771 | E9: Filho(a) | F9: Sim | G9: Revisar | H9: Dados inteiramente fictícios

Sheet Rendimentos
A1: RENDIMENTOS | I1: PROJETO AUTORAL • DADOS FICTÍCIOS
A2: INÍCIO | B2: TITULAR | C2: DEPENDENTES | D2: RENDIMENTOS | E2: BENS | F2: PAGAMENTOS | G2: INFORMES | H2: NOTAS | I2: GUIA
A3: Centralize fontes pagadoras, valores e comprovantes sem calcular o imposto devido.
A5: REGISTROS — 4 EXEMPLO(S) FICTÍCIO(S) PREENCHIDO(S)
A6: Adicione novas linhas dentro da tabela. Células azul-claro são editáveis; colunas cinza contêm fórmulas.
A8: ID | B8: Categoria | C8: Fonte pagadora | D8: CPF/CNPJ | E8: Valor bruto | F8: IRRF | G8: INSS | H8: Documento | I8: Status | J8: Observações
A9: REN-001 | B9: Trabalho assalariado | C9: Empresa Horizonte Ltda. | D9: 00.000.000/0001-00 | E9: 84000 | F9: 7800 | G9: 6300 | H9: informe_empresa_2025.pdf | I9: Conferido | J9: Exemplo fictício
A10: REN-002 | B10: Rendimentos isentos | C10: Banco Aurora S.A. | D10: 00.000.000/0002-00 | E10: 1650.35 | F10: 0 | G10: 0 | H10: informe_banco_2025.pdf | I10: Conferido | J10: Poupança — exemplo
A11: REN-003 | B11: Tributação exclusiva | C11: Corretora Modelo S.A. | D11: 00.000.000/0003-00 | E11: 980.4 | F11: 0 | G11: 0 | H11: informe_corretora_2025.pdf | I11: Recebido | J11: Conferir classificação
A12: REN-004 | B12: Trabalho autônomo | C12: Clientes diversos | D12: N/A | E12: 7200 | F12: 0 | G12: 960 | H12: livro_caixa_exemplo.xlsx | I12: Pendente | J12: Consolidar recibos

Sheet Bens
A1: BENS E DIREITOS | I1: PROJETO AUTORAL • DADOS FICTÍCIOS
A2: INÍCIO | B2: TITULAR | C2: DEPENDENTES | D2: RENDIMENTOS | E2: BENS | F2: PAGAMENTOS | G2: INFORMES | H2: NOTAS | I2: GUIA
A3: Compare os valores declarados no ano anterior com a situação atual e mantenha o documento de origem.
A5: REGISTROS — 4 EXEMPLO(S) FICTÍCIO(S) PREENCHIDO(S)
A6: Adicione novas linhas dentro da tabela. Células azul-claro são editáveis; colunas cinza contêm fórmulas.
A8: ID | B8: Grupo | C8: Código | D8: Descrição | E8: País | F8: Aquisição | G8: Situação anterior | H8: Situação atual | I8: Documento | J8: Status | K8: Observações
A9: BEM-001 | B9: Contas e depósitos | C9: 06.01 | D9: Conta corrente fictícia | E9: Brasil | F9: 44265 | G9: 4200 | H9: 6850.25 | I9: extrato_conta_2025.pdf | J9: Conferido | K9: Exemplo fictício
A10: BEM-002 | B10: Aplicações e investimentos | C10: 04.02 | D10: Aplicação de renda fixa fictícia | E10: Brasil | F10: 44788 | G10: 21000 | H10: 27800.5 | I10: informe_investimento_2025.pdf | J10: Recebido | K10: Conferir rendimentos
A11: BEM-003 | B11: Veículos | C11: 02.01 | D11: Veículo de demonstração | E11: Brasil | F11: 44002 | G11: 58000 | H11: 58000 | I11: documento_veiculo.pdf | J11: Conferido | K11: Custo histórico
A12: BEM-004 | B12: Imóveis | C12: 01.12 | D12: Apartamento fictício | E12: Brasil | F12: 43507 | G12: 245000 | H12: 245000 | I12: contrato_imovel_exemplo.pdf | J12: Conferido | K12: Custo histórico

Sheet Pagamentos
A1: PAGAMENTOS | I1: PROJETO AUTORAL • DADOS FICTÍCIOS
A2: INÍCIO | B2: TITULAR | C2: DEPENDENTES | D2: RENDIMENTOS | E2: BENS | F2: PAGAMENTOS | G2: INFORMES | H2: NOTAS | I2: GUIA
A3: Registre pagamentos e reembolsos; a coluna Valor líquido é calculada automaticamente.
A5: REGISTROS — 3 EXEMPLO(S) FICTÍCIO(S) PREENCHIDO(S)
A6: Adicione novas linhas dentro da tabela. Células azul-claro são editáveis; colunas cinza contêm fórmulas.
A8: ID | B8: Categoria | C8: Beneficiário | D8: CPF/CNPJ | E8: Pessoa | F8: Valor pago | G8: Reembolso | H8: Valor líquido | I8: Documento | J8: Status | K8: Observações
A9: PAG-001 | B9: Plano de saúde | C9: Saúde Modelo S.A. | D9: 00.000.000/0004-00 | E9: Titular | F9: 4560 | G9: 0 | H9: =IF(COUNTA(F9:G9)=0,"",MAX(0,F9-G9)) -> 4560 | I9: informe_saude_2025.pdf | J9: Conferido | K9: Exemplo fictício
A10: PAG-002 | B10: Dentista | C10: Clínica Exemplo | D10: 00.000.000/0005-00 | E10: Titular | F10: 1800 | G10: 300 | H10: =IF(COUNTA(F10:G10)=0,"",MAX(0,F10-G10)) -> 1500 | I10: recibos_dentista.pdf | J10: Recebido | K10: Conferir reembolso
A11: PAG-003 | B11: Educação | C11: Escola Demonstração | D11: 00.000.000/0006-00 | E11: Dependente | F11: 6400 | G11: 0 | H11: =IF(COUNTA(F11:G11)=0,"",MAX(0,F11-G11)) -> 6400 | I11: comprovante_escolar.pdf | J11: Pendente | K11: Aguardando informe anual
H12: =IF(COUNTA(F12:G12)=0,"",MAX(0,F12-G12))
H13: =IF(COUNTA(F13:G13)=0,"",MAX(0,F13-G13))
H14: =IF(COUNTA(F14:G14)=0,"",MAX(0,F14-G14))
H15: =IF(COUNTA(F15:G15)=0,"",MAX(0,F15-G15))
H16: =IF(COUNTA(F16:G16)=0,"",MAX(0,F16-G16))
H17: =IF(COUNTA(F17:G17)=0,"",MAX(0,F17-G17))
H18: =IF(COUNTA(F18:G18)=0,"",MAX(0,F18-G18))
H19: =IF(COUNTA(F19:G19)=0,"",MAX(0,F19-G19))
H20: =IF(COUNTA(F20:G20)=0,"",MAX(0,F20-G20))
H21: =IF(COUNTA(F21:G21)=0,"",MAX(0,F21-G21))
H22: =IF(COUNTA(F22:G22)=0,"",MAX(0,F22-G22))
H23: =IF(COUNTA(F23:G23)=0,"",MAX(0,F23-G23))
... H38: =IF(COUNTA(F38:G38)=0,"",MAX(0,F38-G38))

Sheet Informes
A1: INFORMES | I1: PROJETO AUTORAL • DADOS FICTÍCIOS
A2: INÍCIO | B2: TITULAR | C2: DEPENDENTES | D2: RENDIMENTOS | E2: BENS | F2: PAGAMENTOS | G2: INFORMES | H2: NOTAS | I2: GUIA
A3: Use esta tela como checklist central dos documentos necessários para a revisão.
A5: REGISTROS — 8 EXEMPLO(S) FICTÍCIO(S) PREENCHIDO(S)
A6: Adicione novas linhas dentro da tabela. Células azul-claro são editáveis; colunas cinza contêm fórmulas.
A8: ID | B8: Categoria | C8: Fonte/Instituição | D8: Identificador | E8: Documento esperado | F8: Arquivo/Local | G8: Recebido em | H8: Status | I8: Observações
A9: INF-001 | B9: Rendimentos | C9: Empresa Horizonte Ltda. | D9: 00.000.000/0001-00 | E9: Informe de rendimentos | F9: docs/informe_empresa_2025.pdf | G9: 46063 | H9: Conferido | I9: Exemplo fictício
A10: INF-002 | B10: Bancos | C10: Banco Aurora S.A. | D10: 00.000.000/0002-00 | E10: Informe bancário | F10: docs/informe_banco_2025.pdf | G10: 46065 | H10: Conferido | I10: Exemplo fictício
A11: INF-003 | B11: Investimentos | C11: Corretora Modelo S.A. | D11: 00.000.000/0003-00 | E11: Informe da corretora | F11: docs/informe_corretora_2025.pdf | G11: 46071 | H11: Recebido | I11: Conferir classificação
A12: INF-004 | B12: Saúde | C12: Saúde Modelo S.A. | D12: 00.000.000/0004-00 | E12: Informe do plano | F12: docs/informe_saude_2025.pdf | G12: 46068 | H12: Conferido | I12: Exemplo fictício
A13: INF-005 | B13: Saúde | C13: Clínica Exemplo | D13: 00.000.000/0005-00 | E13: Recibos e reembolsos | F13: docs/recibos_dentista.pdf | G13: 46073 | H13: Recebido | I13: Conferir reembolso
A14: INF-006 | B14: Educação | C14: Escola Demonstração | D14: 00.000.000/0006-00 | E14: Comprovante anual | F14: docs/comprovante_escolar.pdf | H14: Pendente | I14: Solicitar à instituição
A15: INF-007 | B15: Previdência | C15: INSS — exemplo | D15: N/A | E15: Extrato previdenciário | F15: docs/extrato_inss.pdf | G15: 46067 | H15: Conferido | I15: Exemplo fictício
A16: INF-008 | B16: Bens e direitos | C16: Órgão de trânsito — exemplo | D16: N/A | E16: Documento do veículo | F16: docs/documento_veiculo.pdf | G16: 46050 | H16: Conferido | I16: Exemplo fictício

Sheet Notas
A1: NOTAS E PENDÊNCIAS | I1: PROJETO AUTORAL • DADOS FICTÍCIOS
A2: INÍCIO | B2: TITULAR | C2: DEPENDENTES | D2: RENDIMENTOS | E2: BENS | F2: PAGAMENTOS | G2: INFORMES | H2: NOTAS | I2: GUIA
A3: Organize ações de conferência com prioridade, prazo e alerta automático.
A5: REGISTROS — 3 EXEMPLO(S) FICTÍCIO(S) PREENCHIDO(S)
A6: Adicione novas linhas dentro da tabela. Células azul-claro são editáveis; colunas cinza contêm fórmulas.
A8: ID | B8: Categoria | C8: Assunto | D8: Nota | E8: Prioridade | F8: Prazo | G8: Status | H8: Alerta | I8: Responsável
A9: NOT-001 | B9: Rendimento | C9: Conferir informe da corretora | D9: Validar a classificação antes da revisão final. | E9: Alta | F9: 46127 | G9: Em andamento | H9: =IF(A9="","",IF(G9="Concluída","OK",IF(AND(F9<>"",F9<TODAY()),"ATRASADA","ABERTA"))) -> ATRASADA | I9: Titular
A10: NOT-002 | B10: Informe | C10: Solicitar comprovante escolar | D10: Pedir o documento anual à instituição. | E10: Alta | F10: 46132 | G10: Aberta | H10: =IF(A10="","",IF(G10="Concluída","OK",IF(AND(F10<>"",F10<TODAY()),"ATRASADA","ABERTA"))) -> ATRASADA | I10: Titular
A11: NOT-003 | B11: Titular | C11: Revisar dados cadastrais | D11: Confirmar endereço e telefone da cópia privada. | E11: Média | F11: 46137 | G11: Concluída | H11: =IF(A11="","",IF(G11="Concluída","OK",IF(AND(F11<>"",F11<TODAY()),"ATRASADA","ABERTA"))) -> OK | I11: Titular
H12: =IF(A12="","",IF(G12="Concluída","OK",IF(AND(F12<>"",F12<TODAY()),"ATRASADA","ABERTA")))
H13: =IF(A13="","",IF(G13="Concluída","OK",IF(AND(F13<>"",F13<TODAY()),"ATRASADA","ABERTA")))
H14: =IF(A14="","",IF(G14="Concluída","OK",IF(AND(F14<>"",F14<TODAY()),"ATRASADA","ABERTA")))
H15: =IF(A15="","",IF(G15="Concluída","OK",IF(AND(F15<>"",F15<TODAY()),"ATRASADA","ABERTA")))
H16: =IF(A16="","",IF(G16="Concluída","OK",IF(AND(F16<>"",F16<TODAY()),"ATRASADA","ABERTA")))
H17: =IF(A17="","",IF(G17="Concluída","OK",IF(AND(F17<>"",F17<TODAY()),"ATRASADA","ABERTA")))
H18: =IF(A18="","",IF(G18="Concluída","OK",IF(AND(F18<>"",F18<TODAY()),"ATRASADA","ABERTA")))
H19: =IF(A19="","",IF(G19="Concluída","OK",IF(AND(F19<>"",F19<TODAY()),"ATRASADA","ABERTA")))
H20: =IF(A20="","",IF(G20="Concluída","OK",IF(AND(F20<>"",F20<TODAY()),"ATRASADA","ABERTA")))
H21: =IF(A21="","",IF(G21="Concluída","OK",IF(AND(F21<>"",F21<TODAY()),"ATRASADA","ABERTA")))
H22: =IF(A22="","",IF(G22="Concluída","OK",IF(AND(F22<>"",F22<TODAY()),"ATRASADA","ABERTA")))
H23: =IF(A23="","",IF(G23="Concluída","OK",IF(AND(F23<>"",F23<TODAY()),"ATRASADA","ABERTA")))
... H38: =IF(A38="","",IF(G38="Concluída","OK",IF(AND(F38<>"",F38<TODAY()),"ATRASADA","ABERTA")))

Sheet Guia
A1: GUIA DE USO | I1: PROJETO AUTORAL • DADOS FICTÍCIOS
A2: INÍCIO | B2: TITULAR | C2: DEPENDENTES | D2: RENDIMENTOS | E2: BENS | F2: PAGAMENTOS | G2: INFORMES | H2: NOTAS | I2: GUIA
A3: Roteiro de preenchimento, privacidade e validação do IR Panorama.
B5: 1. Antes de começar | C5: Baixe o modelo, salve uma cópia privada e mantenha o arquivo publicado apenas com dados fictícios. Defina o ano-calendário no painel.
B8: 2. Titular e dependentes | C8: Substitua os exemplos na cópia privada. Revise CPF, datas, relação de dependência e dados cadastrais com os documentos oficiais.
B11: 3. Rendimentos | C11: Inclua uma linha por fonte pagadora e transcreva valores apenas dos informes oficiais. A planilha soma valores; ela não calcula imposto devido.
B14: 4. Bens e direitos | C14: Use o grupo e o código apenas como organização preliminar. Compare os valores com a declaração anterior e confirme as regras oficiais antes de transmitir.
B17: 5. Pagamentos | C17: Informe valor pago e reembolso. Valor líquido = valor pago − reembolso, limitado a zero. Guarde recibos e identifique titular ou dependente.
B20: 6. Informes | C20: Atualize o status para Pendente, Recebido, Conferido ou Não se aplica. O painel calcula o percentual concluído e destaca pendências.
B23: 7. Notas | C23: Crie ações com prioridade e prazo. O alerta mostra ATRASADA quando a data passou e a ação ainda não foi concluída.
B26: 8. Links rápidos | C26: Os botões do painel abrem apenas páginas oficiais. Este projeto não usa API, não envia dados e não possui macro.
B29: 9. Conferência final | C29: Compare tudo com os documentos, a declaração anterior e o sistema oficial da Receita Federal. Procure orientação profissional em situações específicas.
B32: 10. Segurança | C32: Não armazene a cópia real em repositório público, pasta compartilhada ou serviço sem proteção. Use senha do dispositivo, backup criptografado e descarte seguro de cópias.
B35: IMPORTANTE: o IR Panorama é um organizador educacional e não substitui o programa oficial, a legislação vigente ou orientação de contador/advogado. Nenhum dado real foi incluído neste arquivo.
B39: Autoria: 0Barone (@gabrielnasciimentoleandro-arch)
B42: VOLTAR AO PAINEL

Sheet Apoio
A1: Listas internas para validação de dados — IR Panorama
A3: lista_status_documento | B3: lista_categorias_rendimento | C3: lista_grupos_bens | D3: lista_categorias_pagamento | E3: lista_prioridades | F3: lista_status_nota | G3: lista_estados_civis | H3: lista_ufs | I3: lista_relacoes_dependente | J3: lista_sim_nao | K3: lista_titular_dependente | L3: lista_categorias_informe | M3: lista_tipos_declaracao | N3: lista_status_cadastro | O3: lista_categorias_nota | P3: lista_paises
A4: Pendente | B4: Trabalho assalariado | C4: Imóveis | D4: Plano de saúde | E4: Baixa | F4: Aberta | G4: Solteiro(a) | H4: AC | I4: Cônjuge/Companheiro(a) | J4: Sim | K4: Titular | L4: Rendimentos | M4: Original | N4: Pendente | O4: Titular | P4: Brasil
A5: Recebido | B5: Trabalho autônomo | C5: Veículos | D5: Médico/Hospital | E5: Média | F5: Em andamento | G5: Casado(a) | H5: AL | I5: Filho(a) | J5: Não | K5: Dependente | L5: Bancos | M5: Retificadora | N5: Revisar | O5: Dependente | P5: Estados Unidos
A6: Conferido | B6: Aposentadoria/Pensão | C6: Contas e depósitos | D6: Dentista | E6: Alta | F6: Concluída | G6: União estável | H6: AP | I6: Enteado(a) | L6: Investimentos | N6: Completo | O6: Rendimento | P6: Portugal
A7: Não se aplica | B7: Rendimentos isentos | C7: Aplicações e investimentos | D7: Educação | E7: Crítica | G7: Separado(a) | H7: AM | I7: Pai/Mãe | L7: Saúde | O7: Bem | P7: Outro
B8: Tributação exclusiva | C8: Participações societárias | D8: Previdência | G8: Divorciado(a) | H8: BA | I8: Avô/Avó | L8: Educação | O8: Pagamento
B9: Aluguéis | C9: Criptoativos | D9: Pensão alimentícia | G9: Viúvo(a) | H9: CE | I9: Irmão(ã) | L9: Previdência | O9: Informe
B10: Exterior | C10: Créditos | D10: Profissional liberal | H10: DF | I10: Neto(a) | L10: Bens e direitos | O10: Conferência final
B11: Outros | C11: Outros bens | D11: Outros | H11: ES | I11: Outro permitido | L11: Dívidas | O11: Outro
H12: GO | L12: Outros
H13: MA
H14: MT
H15: MS
H16: MG
H17: PA
H18: PB
H19: PR
H20: PE
H21: PI
H22: RJ
H23: RN
H24: RS
... H30: TO
